{
  "moduleFileExtensions": ["js", "json", "ts"],
  "rootDir": ".",
  "testEnvironment": "node",
  "testRegex": "test/e2e/.*\\.e2e-spec\\.ts$",
  "transform": {
    "^.+\\.(t|j)s$": "ts-jest"
  },
  "moduleNameMapper": {
    "^@domain/(.*)$": "<rootDir>/src/domain/$1",
    "^@use-cases/(.*)$": "<rootDir>/src/use-cases/$1",
    "^@adapters/(.*)$": "<rootDir>/src/adapters/$1",
    "^@infrastructure/(.*)$": "<rootDir>/src/infrastructure/$1",
    "^@modules/(.*)$": "<rootDir>/src/modules/$1",
    "^test/(.*)$": "<rootDir>/test/$1"
  },
  "setupFiles": ["<rootDir>/test/e2e/setup/env.setup.ts"],
  "coverageDirectory": "./coverage-e2e",
  "collectCoverageFrom": [
    "src/**/*.(t|j)s",
    "!src/main.ts",
    "!src/**/*.module.ts",
    "!src/**/*.config.ts"
  ]
}
